fiberhttp/__init__.py
fiberhttp/__version__.py
fiberhttp/_build.py
fiberhttp/_client_file.py
fiberhttp/_client_proxy.py
fiberhttp/_connections.py
fiberhttp/_exceptions.py
fiberhttp/_methods.py
fiberhttp/_responses.py
fiberhttp-5.2.dist-info/LICENSE
fiberhttp-5.2.dist-info/METADATA
fiberhttp-5.2.dist-info/NOTICE
fiberhttp-5.2.dist-info/WHEEL
fiberhttp-5.2.dist-info/top_level.txt
fiberhttp-5.2.dist-info/RECORD
