Metadata-Version: 2.1
Name: fiberhttp
Version: 5.2
Summary: High Performance HTTP Requests Library
Home-page: https://www.github.com/xsxo/fiberhttp
Author: xsxo
License: Apache-2.0
Project-URL: Source, https://github.com/xsxo/fiberhttp
Classifier: Programming Language :: Python :: 3
Classifier: Programming Language :: Python :: 3.8
Classifier: Programming Language :: Python :: 3.9
Classifier: Programming Language :: Python :: 3.10
Classifier: Programming Language :: Python :: 3.11
Classifier: Programming Language :: Python :: 3.12
Classifier: Operating System :: OS Independent
Classifier: License :: OSI Approved :: Apache Software License
License-File: LICENSE
License-File: NOTICE
Requires-Dist: certifi>=2017.4.17
